idbt/__init__.py
idbt/main.py
idbt/compiler/__init__.py
idbt/context/i_unit_test.py
idbt/events/types.py
idbt/exception/__init__.py
idbt/graph/selector.py
idbt/loader/__init__.py
idbt/manifest/__init__.py
idbt/manifest/base.py
idbt/manifest/i_unit_test.py
idbt/parser/base.py
idbt/parser/yaml_parser.py
idbt/task/i_unit_test.py
idbt/task/seed.py
idbt/unittest_func_hook/__init__.py
idbt-0.0.7.dist-info/METADATA
idbt-0.0.7.dist-info/WHEEL
idbt-0.0.7.dist-info/entry_points.txt
idbt-0.0.7.dist-info/top_level.txt
idbt-0.0.7.dist-info/RECORD
