Metadata-Version: 2.1
Name: idbt
Version: 0.0.7
Summary: This is inter-k internal tool to help data practice becomes more testable
Home-page: https://gitlab.inter-k.com/inter-k/internal-software/rnd/idbt
Author: Bảo Phan
Author-email: bao.phan1441@gmail.com
Classifier: Development Status :: 5 - Production/Stable
Classifier: License :: OSI Approved :: Apache Software License
Classifier: Operating System :: Microsoft :: Windows
Classifier: Operating System :: MacOS :: MacOS X
Classifier: Operating System :: POSIX :: Linux
Classifier: Programming Language :: Python :: 3.8
Classifier: Programming Language :: Python :: 3.9
Classifier: Programming Language :: Python :: 3.10
Classifier: Programming Language :: Python :: 3.11
Classifier: Programming Language :: Python :: 3.12
Requires-Python: >=3.8
Requires-Dist: dbt-core ==1.7.15
